openblacklist/__init__.py
openblacklist/main.py
openblacklist/method/Model.py
openblacklist/method/Type.py
openblacklist-1.1.3.dist-info/LICENSE
openblacklist-1.1.3.dist-info/METADATA
openblacklist-1.1.3.dist-info/WHEEL
openblacklist-1.1.3.dist-info/RECORD
