Metadata-Version: 2.1
Name: openblacklist
Version: 1.1.3
Summary: Official client for openblacklist API
Home-page: https://openbl.clarty.org/
License: MIT
Author: Awakno
Author-email: contact@awakno.fr
Requires-Python: >=3.8.1,<4.0.0
Classifier: License :: OSI Approved :: MIT License
Classifier: Programming Language :: Python :: 3
Classifier: Programming Language :: Python :: 3.9
Classifier: Programming Language :: Python :: 3.10
Classifier: Programming Language :: Python :: 3.11
Classifier: Programming Language :: Python :: 3.12
Classifier: Programming Language :: Python :: 3.13
Requires-Dist: aiohttp (>=3.9.5,<4.0.0)
Requires-Dist: fastapi (>=0.115.5,<0.116.0)
Requires-Dist: pydantic (>=2.8.2,<3.0.0)
Requires-Dist: uvicorn (==0.32.1)
Project-URL: Repository, https://github.com/Awakno/OpenBlacklist-py
